README.md
pyproject.toml
setup.py
src/corbett/__init__.py
src/corbett/__main__.py
src/corbett/app.py
src/corbett/cli.py
src/corbett/client.py
src/corbett/config.py
src/corbett/installer.py
src/corbett/models.py
src/corbett/services.py
src/corbett/snowflake.py
src/corbett.egg-info/PKG-INFO
src/corbett.egg-info/SOURCES.txt
src/corbett.egg-info/dependency_links.txt
src/corbett.egg-info/entry_points.txt
src/corbett.egg-info/requires.txt
src/corbett.egg-info/top_level.txt
src/corbett/apps/debugger/__init__.py
src/corbett/apps/debugger/app.py
src/corbett/apps/debugger/credentials.py
src/corbett/apps/debugger/handler.py
src/corbett/apps/gsheets/__init__.py
src/corbett/apps/gsheets/app.py
src/corbett/apps/gsheets/credentials.py
src/corbett/apps/gsheets/handler.py
tests/test_cli.py